{
	"info": {
		"_postman_id": "9e4578db-ae17-4763-8a77-0195a13cdcb6",
		"name": "CantinR",
		"description": "DHBW Mannheim WWI15SCB Mobile Project\n\nhttps://github.com/mobileDHBW18/backend",
		"schema": "https://schema.getpostman.com/json/collection/v2.1.0/collection.json"
	},
	"item": [
		{
			"name": "MENSA",
			"description": "",
			"item": [
				{
					"name": "CREATE",
					"request": {
						"method": "PUT",
						"header": [
							{
								"key": "Content-Type",
								"value": "application/json"
							}
						],
						"body": {
							"mode": "raw",
							"raw": "{\r\n\t\"name\": \"mensa2\",\r\n\t\"uni\": \"DHBW Mannheim\",\r\n\t\"location\": \"Seckenheimer Landstr\",\r\n\t\"cords\": {\r\n\t\t\"lat\": 30.0138,\r\n\t\t\"long\": 501.13\r\n\t}\r\n}"
						},
						"url": {
							"raw": "https://xqo9cbx1hj.execute-api.eu-central-1.amazonaws.com/dev/mensa?",
							"protocol": "https",
							"host": [
								"xqo9cbx1hj",
								"execute-api",
								"eu-central-1",
								"amazonaws",
								"com"
							],
							"path": [
								"dev",
								"mensa"
							],
							"query": [
								{
									"key": "radius",
									"value": "24km",
									"disabled": true
								}
							]
						}
					},
					"response": []
				},
				{
					"name": "GET ALL",
					"request": {
						"method": "GET",
						"header": [
							{
								"key": "Content-Type",
								"value": "application/json"
							}
						],
						"body": {
							"mode": "raw",
							"raw": "{\r\n\t\"name\": \"mensa1\",\r\n\t\"uni\": \"DHBW Mannheim\",\r\n\t\"location\": \"Seckenheimer Landstr\",\r\n\t\"cords\": {\r\n\t\t\"lat\": 39.0138,\r\n\t\t\"long\": 301.13\r\n\t}\r\n}"
						},
						"url": {
							"raw": "https://xqo9cbx1hj.execute-api.eu-central-1.amazonaws.com/dev/mensa?",
							"protocol": "https",
							"host": [
								"xqo9cbx1hj",
								"execute-api",
								"eu-central-1",
								"amazonaws",
								"com"
							],
							"path": [
								"dev",
								"mensa"
							],
							"query": [
								{
									"key": "radius",
									"value": "24km",
									"disabled": true
								}
							]
						}
					},
					"response": []
				},
				{
					"name": "GET SPECIFIC",
					"request": {
						"method": "GET",
						"header": [
							{
								"key": "Content-Type",
								"value": "application/json"
							}
						],
						"body": {
							"mode": "raw",
							"raw": "{\r\n\t\"name\": \"mensa1\",\r\n\t\"uni\": \"DHBW Mannheim\",\r\n\t\"location\": \"Seckenheimer Landstr\",\r\n\t\"cords\": {\r\n\t\t\"lat\": 39.0138,\r\n\t\t\"long\": 301.13\r\n\t}\r\n}"
						},
						"url": {
							"raw": "https://xqo9cbx1hj.execute-api.eu-central-1.amazonaws.com/dev/mensa/ca2a5b80-6a58-11e8-9239-1bfe8cfba77b?",
							"protocol": "https",
							"host": [
								"xqo9cbx1hj",
								"execute-api",
								"eu-central-1",
								"amazonaws",
								"com"
							],
							"path": [
								"dev",
								"mensa",
								"ca2a5b80-6a58-11e8-9239-1bfe8cfba77b"
							],
							"query": [
								{
									"key": "radius",
									"value": "24km",
									"disabled": true
								}
							]
						},
						"description": "Uses \"id\" property for identification\n\nGET /mensa/{id}"
					},
					"response": []
				}
			]
		},
		{
			"name": "MEALS",
			"description": "",
			"item": [
				{
					"name": "CREATE",
					"request": {
						"method": "PUT",
						"header": [
							{
								"key": "Content-Type",
								"value": "application/json"
							}
						],
						"body": {
							"mode": "raw",
							"raw": "{\r\n\t\"name\": \"gericht3\",\r\n\t\"mensa\": \"DHBW Mannheim1\",\r\n\t\"categories\": {\r\n\t\t\"veg\": true,\r\n\t\t\"chicken\": false,\r\n\t\t\"beef\": false,\r\n\t\t\"gluten\": true,\r\n\t\t\"pig\": false,\r\n\t\t\"fish\": false\r\n\t},\r\n\t\"ingrediences\": \"blah blah\",\r\n\t\"allergens\": \"whatever\",\r\n\t\"price\": 5.99\r\n}"
						},
						"url": {
							"raw": "https://xqo9cbx1hj.execute-api.eu-central-1.amazonaws.com/dev/meals?",
							"protocol": "https",
							"host": [
								"xqo9cbx1hj",
								"execute-api",
								"eu-central-1",
								"amazonaws",
								"com"
							],
							"path": [
								"dev",
								"meals"
							],
							"query": [
								{
									"key": "radius",
									"value": "24km",
									"disabled": true
								}
							]
						}
					},
					"response": []
				},
				{
					"name": "GET ALL / SEARCH",
					"request": {
						"method": "GET",
						"header": [
							{
								"key": "Content-Type",
								"value": "application/json"
							}
						],
						"body": {
							"mode": "raw",
							"raw": "{\r\n\t\"name\": \"mensa1\",\r\n\t\"uni\": \"DHBW Mannheim\",\r\n\t\"location\": \"Seckenheimer Landstr\",\r\n\t\"cords\": {\r\n\t\t\"lat\": 39.0138,\r\n\t\t\"long\": 301.13\r\n\t}\r\n}"
						},
						"url": {
							"raw": "https://xqo9cbx1hj.execute-api.eu-central-1.amazonaws.com/dev/meals?date=2018-06-08&mensa=DHBW Mannheim1",
							"protocol": "https",
							"host": [
								"xqo9cbx1hj",
								"execute-api",
								"eu-central-1",
								"amazonaws",
								"com"
							],
							"path": [
								"dev",
								"meals"
							],
							"query": [
								{
									"key": "date",
									"value": "2018-06-08"
								},
								{
									"key": "mensa",
									"value": "DHBW Mannheim1"
								}
							]
						},
						"description": "über QS Params Suche eingrenzen\n\nParams \"date\" und \"mensa\" erlaubt.\nSuche wird nur ausgeführt wenn beide Parameter vorhanden sind."
					},
					"response": []
				},
				{
					"name": "GET SPECIFIC",
					"request": {
						"method": "GET",
						"header": [
							{
								"key": "Content-Type",
								"value": "application/json"
							}
						],
						"body": {
							"mode": "raw",
							"raw": "{\r\n\t\"name\": \"mensa1\",\r\n\t\"uni\": \"DHBW Mannheim\",\r\n\t\"location\": \"Seckenheimer Landstr\",\r\n\t\"cords\": {\r\n\t\t\"lat\": 39.0138,\r\n\t\t\"long\": 301.13\r\n\t}\r\n}"
						},
						"url": {
							"raw": "https://xqo9cbx1hj.execute-api.eu-central-1.amazonaws.com/dev/meals/751085c0-6a5d-11e8-adc6-cf6b3e139973?",
							"protocol": "https",
							"host": [
								"xqo9cbx1hj",
								"execute-api",
								"eu-central-1",
								"amazonaws",
								"com"
							],
							"path": [
								"dev",
								"meals",
								"751085c0-6a5d-11e8-adc6-cf6b3e139973"
							],
							"query": [
								{
									"key": "date",
									"value": "2018-06-08",
									"disabled": true
								}
							]
						},
						"description": "Uses \"id\" property for identification\r\nGET /meals/{id}"
					},
					"response": []
				},
				{
					"name": "RATE",
					"request": {
						"method": "POST",
						"header": [
							{
								"key": "Content-Type",
								"value": "application/json"
							}
						],
						"body": {
							"mode": "raw",
							"raw": "{\r\n\t\"rating\": 4.7\r\n}"
						},
						"url": {
							"raw": "https://xqo9cbx1hj.execute-api.eu-central-1.amazonaws.com/dev/meals/751085c0-6a5d-11e8-adc6-cf6b3e139973?",
							"protocol": "https",
							"host": [
								"xqo9cbx1hj",
								"execute-api",
								"eu-central-1",
								"amazonaws",
								"com"
							],
							"path": [
								"dev",
								"meals",
								"751085c0-6a5d-11e8-adc6-cf6b3e139973"
							],
							"query": [
								{
									"key": "radius",
									"value": "24km",
									"disabled": true
								}
							]
						}
					},
					"response": []
				}
			]
		}
	]
}